dstkc/__init__.py
dstkc/tkc.py
dstkc-0.1.4.dist-info/LICENSE
dstkc-0.1.4.dist-info/METADATA
dstkc-0.1.4.dist-info/WHEEL
dstkc-0.1.4.dist-info/top_level.txt
dstkc-0.1.4.dist-info/RECORD
