Metadata-Version: 2.1
Name: dstkc
Version: 0.1.4
Summary: data science preprocessing toolkit and container
Home-page: https://github.com/GreeneWoods/dstkc
Author: BG
License: UNKNOWN
Platform: UNKNOWN
Classifier: Programming Language :: Python :: 3
Classifier: License :: OSI Approved :: GNU Affero General Public License v3
Classifier: Operating System :: OS Independent
Requires-Python: >=3.6
License-File: LICENSE
